{
  "weapp": {
    "appid": "微信小程戏appid",
    "privateKeyPath": "密钥文件相对项目根目录的相对路径，例如 key/private.appid.key",
    "enable": "开启/关闭构建",
    "projectPath": "项目构建目录"
  },
  "tt": {
    "email": "字节小程序邮箱",
    "password": "字节小程序密码",
    "enable": "开启/关闭构建",
    "projectPath": "项目构建目录"
  },
  "alipay": {
    "appId": "支付宝小程序appId",
    "toolId": "工具id",
    "privateKeyPath": "密钥文件相对项目根目录的相对路径，例如 key/pkcs8-private-pem",
    "enable": "开启/关闭构建",
    "version": "支付宝小程序版本号",
    "projectPath": "项目构建目录"
  },
  "swan": {
    "token": "鉴权需要的token令牌",
    "enable": "开启/关闭构建",
    "projectPath": "项目构建目录",
    "minSwanVersion": "对应版本基础库"
  },
  "noticeCardConfig": {
    "buildUrl": "小程序构建包下载地址",
    "weappQrCodeUrl": "微信小程序二维码访问地址",
    "alipayQrCodeUrl": "支付宝小程序二维码访问地址",
    "swanQrCodeUrl": "百度小程序二维码访问地址",
    "ttQrCodeUrl": "字节小程序二维码访问地址",
    "jdQrCodeUrl": "京东小程序二维码访问地址"
  },
  "deployBaseUrl": "发布 base url",
  "defaultWeappQrUrl": "微信体验码默认地址",
  "defaultJdQrUrl": "京东体验码默认地址",
  "env": "编译需要用的环境变量",
  "webhookUrl": "构建成功后的webhook回调地址",
  "version": "1.0.0",
  "isGenerateVersion": "是否根据日期生成版本号，格式主版本号+日期",
  "majorVersion": "当前主版本号",
  "desc": "版本描述"
}
